{
  "slug": "2-18-2025",
  "campaignId": "715deeb26e",
  "title": "Plateau Ahead, Meta HQ & Off-Markets",
  "description": "Comparing Austin metro trends with downtown Austin real estate, suggesting downtown lags by 12 months, plus Meta's potential HQ move and new bike lane parking ordinance.",
  "date": "2025-02-18",
  "author": "Jacob Hannusch",
  "tags": [
    "downtown austin",
    "condos",
    "market plateau",
    "meta",
    "off-market"
  ],
  "keywords": [
    "downtown austin market plateau",
    "meta headquarters austin",
    "austin downtown strategic initiative",
    "bike lane parking ordinance austin"
  ],
  "thumbnail": "/images/newsletters/2-18-2025/img-004.jpg",
  "category": "newsletter",
  "status": "published",
  "readingTime": 2
}