{
  "slug": "12-9-2025",
  "campaignId": "4e47717e7b",
  "title": "Infrastructure Projects, Shiner's Saloon, & Off-Markets",
  "description": "Downtown Austin faces $20B in infrastructure projects through 2033, Shiner's Saloon is set for redevelopment, and autonomous vehicle safety data shows promising results.",
  "date": "2025-12-09",
  "author": "Jacob Hannusch",
  "tags": [
    "downtown austin",
    "infrastructure",
    "development",
    "off-market",
    "condos"
  ],
  "keywords": [
    "austin infrastructure projects",
    "shiners saloon redevelopment",
    "downtown austin condos",
    "natiivo condos",
    "independent condos austin"
  ],
  "thumbnail": "/images/newsletters/12-9-2025/img-004.jpg",
  "category": "newsletter",
  "status": "published",
  "readingTime": 2
}